Metadata-Version: 2.1
Name: varhash
Version: 0.0.3
Summary: Implementation of VAR Hash in Python
Home-page: https://github.com/rishabhc9
Author: Rishabh Chopda
Author-email: aaditchopda2@gmail.com
License: MIT
Keywords: varhash,hash,hashing,cryptography
Platform: UNKNOWN
Classifier: Development Status :: 5 - Production/Stable
Classifier: Intended Audience :: Education
Classifier: Operating System :: OS Independent
Classifier: License :: OSI Approved :: MIT License
Classifier: Programming Language :: Python :: 3
License-File: LICENSE.txt
